DocUMust-0.0.7.dist-info/DESCRIPTION.rst
DocUMust-0.0.7.dist-info/METADATA
DocUMust-0.0.7.dist-info/RECORD
DocUMust-0.0.7.dist-info/WHEEL
DocUMust-0.0.7.dist-info/entry_points.txt
DocUMust-0.0.7.dist-info/metadata.json
DocUMust-0.0.7.dist-info/top_level.txt
documust/__init__.py
documust/cli.py
documust/utils/__init__.py
documust/utils/path_utils.py
