Metadata-Version: 2.0
Name: DocUMust
Version: 0.0.7
Summary: Lets make sure you don't forget to document this time.
Home-page: https://github.com/tsarpaul/DocUMust
Author: Paul Litvak
Author-email: litvakpol@012.net.il
License: MIT License
Keywords: documentation,python,tool
Platform: UNKNOWN
Requires-Dist: crayons (==0.1.2)
Requires-Dist: six (==1.10.0)
